{"config":{"output_file":null,"full_docs":false,"pub_only":true,"reachable_only":true,"distro_crate":false,"signatures":false,"borrow_data":false},"version":"0.19.1","compilation":{"directory":"/home/users/u6632448/.cargo/registry/src/github.com-1ecc6299db9ec823/glob-0.3.0","program":"/home/users/u6632448/.rustup/toolchains/stable-x86_64-unknown-linux-gnu/bin/rls","arguments":["--crate-name","glob","/home/users/u6632448/.cargo/registry/src/github.com-1ecc6299db9ec823/glob-0.3.0/src/lib.rs","--json=diagnostic-rendered-ansi,artifacts","--crate-type","lib","--emit=dep-info,metadata,link","-C","embed-bitcode=no","-C","debuginfo=2","-C","metadata=2b2ec36fd2506c04","-C","extra-filename=-2b2ec36fd2506c04","--out-dir","/home/users/u6632448/pelikan/src/rust/config/target/rls/debug/deps","-L","dependency=/home/users/u6632448/pelikan/src/rust/config/target/rls/debug/deps","--cap-lints","allow","--error-format=json","--sysroot","/home/users/u6632448/.rustup/toolchains/stable-x86_64-unknown-linux-gnu"],"output":"/home/users/u6632448/pelikan/src/rust/config/target/rls/debug/deps/libglob-2b2ec36fd2506c04.rmeta"},"prelude":{"crate_id":{"name":"glob","disambiguator":[6910269473256212587,0]},"crate_root":"/home/users/u6632448/.cargo/registry/src/github.com-1ecc6299db9ec823/glob-0.3.0/src","external_crates":[{"file_name":"/home/users/u6632448/.cargo/registry/src/github.com-1ecc6299db9ec823/glob-0.3.0/src/lib.rs","num":1,"id":{"name":"std","disambiguator":[292688086858374235,0]}},{"file_name":"/home/users/u6632448/.cargo/registry/src/github.com-1ecc6299db9ec823/glob-0.3.0/src/lib.rs","num":2,"id":{"name":"core","disambiguator":[6438385474535706924,0]}},{"file_name":"/home/users/u6632448/.cargo/registry/src/github.com-1ecc6299db9ec823/glob-0.3.0/src/lib.rs","num":3,"id":{"name":"compiler_builtins","disambiguator":[13729837066422225192,0]}},{"file_name":"/home/users/u6632448/.cargo/registry/src/github.com-1ecc6299db9ec823/glob-0.3.0/src/lib.rs","num":4,"id":{"name":"rustc_std_workspace_core","disambiguator":[5402880783377335769,0]}},{"file_name":"/home/users/u6632448/.cargo/registry/src/github.com-1ecc6299db9ec823/glob-0.3.0/src/lib.rs","num":5,"id":{"name":"alloc","disambiguator":[6315666440082044202,0]}},{"file_name":"/home/users/u6632448/.cargo/registry/src/github.com-1ecc6299db9ec823/glob-0.3.0/src/lib.rs","num":6,"id":{"name":"libc","disambiguator":[8715266272784128359,0]}},{"file_name":"/home/users/u6632448/.cargo/registry/src/github.com-1ecc6299db9ec823/glob-0.3.0/src/lib.rs","num":7,"id":{"name":"unwind","disambiguator":[2088041259338434830,0]}},{"file_name":"/home/users/u6632448/.cargo/registry/src/github.com-1ecc6299db9ec823/glob-0.3.0/src/lib.rs","num":8,"id":{"name":"cfg_if","disambiguator":[3489163311945967218,0]}},{"file_name":"/home/users/u6632448/.cargo/registry/src/github.com-1ecc6299db9ec823/glob-0.3.0/src/lib.rs","num":9,"id":{"name":"hashbrown","disambiguator":[751421253572859800,0]}},{"file_name":"/home/users/u6632448/.cargo/registry/src/github.com-1ecc6299db9ec823/glob-0.3.0/src/lib.rs","num":10,"id":{"name":"rustc_std_workspace_alloc","disambiguator":[13041685254533870257,0]}},{"file_name":"/home/users/u6632448/.cargo/registry/src/github.com-1ecc6299db9ec823/glob-0.3.0/src/lib.rs","num":11,"id":{"name":"rustc_demangle","disambiguator":[502015445408459368,0]}},{"file_name":"/home/users/u6632448/.cargo/registry/src/github.com-1ecc6299db9ec823/glob-0.3.0/src/lib.rs","num":12,"id":{"name":"std_detect","disambiguator":[6198952210139392550,0]}},{"file_name":"/home/users/u6632448/.cargo/registry/src/github.com-1ecc6299db9ec823/glob-0.3.0/src/lib.rs","num":13,"id":{"name":"addr2line","disambiguator":[14184030540380960994,0]}},{"file_name":"/home/users/u6632448/.cargo/registry/src/github.com-1ecc6299db9ec823/glob-0.3.0/src/lib.rs","num":14,"id":{"name":"gimli","disambiguator":[18399346483724303225,0]}},{"file_name":"/home/users/u6632448/.cargo/registry/src/github.com-1ecc6299db9ec823/glob-0.3.0/src/lib.rs","num":15,"id":{"name":"object","disambiguator":[15511893313068785759,0]}},{"file_name":"/home/users/u6632448/.cargo/registry/src/github.com-1ecc6299db9ec823/glob-0.3.0/src/lib.rs","num":16,"id":{"name":"memchr","disambiguator":[13348528473392455417,0]}},{"file_name":"/home/users/u6632448/.cargo/registry/src/github.com-1ecc6299db9ec823/glob-0.3.0/src/lib.rs","num":17,"id":{"name":"miniz_oxide","disambiguator":[12356376325519007124,0]}},{"file_name":"/home/users/u6632448/.cargo/registry/src/github.com-1ecc6299db9ec823/glob-0.3.0/src/lib.rs","num":18,"id":{"name":"adler","disambiguator":[7246437135573011264,0]}},{"file_name":"/home/users/u6632448/.cargo/registry/src/github.com-1ecc6299db9ec823/glob-0.3.0/src/lib.rs","num":19,"id":{"name":"panic_unwind","disambiguator":[12319769989328939461,0]}}],"span":{"file_name":"/home/users/u6632448/.cargo/registry/src/github.com-1ecc6299db9ec823/glob-0.3.0/src/lib.rs","byte_start":467,"byte_end":50050,"line_start":11,"line_end":1411,"column_start":1,"column_end":2}},"imports":[],"defs":[{"kind":"Mod","id":{"krate":0,"index":0},"span":{"file_name":"/home/users/u6632448/.cargo/registry/src/github.com-1ecc6299db9ec823/glob-0.3.0/src/lib.rs","byte_start":467,"byte_end":50050,"line_start":11,"line_end":1411,"column_start":1,"column_end":2},"name":"","qualname":"::","value":"/home/users/u6632448/.cargo/registry/src/github.com-1ecc6299db9ec823/glob-0.3.0/src/lib.rs","parent":null,"children":[{"krate":0,"index":1},{"krate":0,"index":2},{"krate":0,"index":3},{"krate":0,"index":6},{"krate":0,"index":9},{"krate":0,"index":12},{"krate":0,"index":15},{"krate":0,"index":18},{"krate":0,"index":19},{"krate":0,"index":22},{"krate":0,"index":25},{"krate":0,"index":28},{"krate":0,"index":31},{"krate":0,"index":34},{"krate":0,"index":35},{"krate":0,"index":36},{"krate":0,"index":38},{"krate":0,"index":39},{"krate":0,"index":41},{"krate":0,"index":42},{"krate":0,"index":43},{"krate":0,"index":45},{"krate":0,"index":46},{"krate":0,"index":48},{"krate":0,"index":49},{"krate":0,"index":51},{"krate":0,"index":52},{"krate":0,"index":54},{"krate":0,"index":55},{"krate":0,"index":56},{"krate":0,"index":58},{"krate":0,"index":59},{"krate":0,"index":61},{"krate":0,"index":62},{"krate":0,"index":64},{"krate":0,"index":65},{"krate":0,"index":67},{"krate":0,"index":68},{"krate":0,"index":70},{"krate":0,"index":76},{"krate":0,"index":77},{"krate":0,"index":136},{"krate":0,"index":139},{"krate":0,"index":82},{"krate":0,"index":86},{"krate":0,"index":89},{"krate":0,"index":91},{"krate":0,"index":93},{"krate":0,"index":94},{"krate":0,"index":141},{"krate":0,"index":144},{"krate":0,"index":98},{"krate":0,"index":100},{"krate":0,"index":146},{"krate":0,"index":150},{"krate":0,"index":152},{"krate":0,"index":153},{"krate":0,"index":156},{"krate":0,"index":157},{"krate":0,"index":159},{"krate":0,"index":161},{"krate":0,"index":163},{"krate":0,"index":166},{"krate":0,"index":168},{"krate":0,"index":102},{"krate":0,"index":104},{"krate":0,"index":170},{"krate":0,"index":186},{"krate":0,"index":188},{"krate":0,"index":189},{"krate":0,"index":192},{"krate":0,"index":193},{"krate":0,"index":195},{"krate":0,"index":197},{"krate":0,"index":199},{"krate":0,"index":202},{"krate":0,"index":204},{"krate":0,"index":212},{"krate":0,"index":213},{"krate":0,"index":215},{"krate":0,"index":216},{"krate":0,"index":219},{"krate":0,"index":220},{"krate":0,"index":222},{"krate":0,"index":224},{"krate":0,"index":226},{"krate":0,"index":229},{"krate":0,"index":231},{"krate":0,"index":238},{"krate":0,"index":239},{"krate":0,"index":241},{"krate":0,"index":242},{"krate":0,"index":107},{"krate":0,"index":108},{"krate":0,"index":109},{"krate":0,"index":110},{"krate":0,"index":123},{"krate":0,"index":131},{"krate":0,"index":132},{"krate":0,"index":133},{"krate":0,"index":244},{"krate":0,"index":248},{"krate":0,"index":249},{"krate":0,"index":251},{"krate":0,"index":252},{"krate":0,"index":255},{"krate":0,"index":256},{"krate":0,"index":258},{"krate":0,"index":260},{"krate":0,"index":262},{"krate":0,"index":265},{"krate":0,"index":134}],"decl_id":null,"docs":" Support for matching file paths against Unix shell style patterns.","sig":null,"attributes":[{"value":"/ Support for matching file paths against Unix shell style patterns.","span":{"file_name":"/home/users/u6632448/.cargo/registry/src/github.com-1ecc6299db9ec823/glob-0.3.0/src/lib.rs","byte_start":467,"byte_end":537,"line_start":11,"line_end":11,"column_start":1,"column_end":71}},{"value":"/","span":{"file_name":"/home/users/u6632448/.cargo/registry/src/github.com-1ecc6299db9ec823/glob-0.3.0/src/lib.rs","byte_start":538,"byte_end":541,"line_start":12,"line_end":12,"column_start":1,"column_end":4}},{"value":"/ The `glob` and `glob_with` functions allow querying the filesystem for all","span":{"file_name":"/home/users/u6632448/.cargo/registry/src/github.com-1ecc6299db9ec823/glob-0.3.0/src/lib.rs","byte_start":542,"byte_end":620,"line_start":13,"line_end":13,"column_start":1,"column_end":79}},{"value":"/ files that match a particular pattern (similar to the libc `glob` function).","span":{"file_name":"/home/users/u6632448/.cargo/registry/src/github.com-1ecc6299db9ec823/glob-0.3.0/src/lib.rs","byte_start":621,"byte_end":701,"line_start":14,"line_end":14,"column_start":1,"column_end":81}},{"value":"/ The methods on the `Pattern` type provide functionality for checking if","span":{"file_name":"/home/users/u6632448/.cargo/registry/src/github.com-1ecc6299db9ec823/glob-0.3.0/src/lib.rs","byte_start":702,"byte_end":777,"line_start":15,"line_end":15,"column_start":1,"column_end":76}},{"value":"/ individual paths match a particular pattern (similar to the libc `fnmatch`","span":{"file_name":"/home/users/u6632448/.cargo/registry/src/github.com-1ecc6299db9ec823/glob-0.3.0/src/lib.rs","byte_start":778,"byte_end":856,"line_start":16,"line_end":16,"column_start":1,"column_end":79}},{"value":"/ function).","span":{"file_name":"/home/users/u6632448/.cargo/registry/src/github.com-1ecc6299db9ec823/glob-0.3.0/src/lib.rs","byte_start":857,"byte_end":871,"line_start":17,"line_end":17,"column_start":1,"column_end":15}},{"value":"/","span":{"file_name":"/home/users/u6632448/.cargo/registry/src/github.com-1ecc6299db9ec823/glob-0.3.0/src/lib.rs","byte_start":872,"byte_end":875,"line_start":18,"line_end":18,"column_start":1,"column_end":4}},{"value":"/ For consistency across platforms, and for Windows support, this module","span":{"file_name":"/home/users/u6632448/.cargo/registry/src/github.com-1ecc6299db9ec823/glob-0.3.0/src/lib.rs","byte_start":876,"byte_end":950,"line_start":19,"line_end":19,"column_start":1,"column_end":75}},{"value":"/ is implemented entirely in Rust rather than deferring to the libc","span":{"file_name":"/home/users/u6632448/.cargo/registry/src/github.com-1ecc6299db9ec823/glob-0.3.0/src/lib.rs","byte_start":951,"byte_end":1020,"line_start":20,"line_end":20,"column_start":1,"column_end":70}},{"value":"/ `glob`/`fnmatch` functions.","span":{"file_name":"/home/users/u6632448/.cargo/registry/src/github.com-1ecc6299db9ec823/glob-0.3.0/src/lib.rs","byte_start":1021,"byte_end":1052,"line_start":21,"line_end":21,"column_start":1,"column_end":32}},{"value":"/","span":{"file_name":"/home/users/u6632448/.cargo/registry/src/github.com-1ecc6299db9ec823/glob-0.3.0/src/lib.rs","byte_start":1053,"byte_end":1056,"line_start":22,"line_end":22,"column_start":1,"column_end":4}},{"value":"/ # Examples","span":{"file_name":"/home/users/u6632448/.cargo/registry/src/github.com-1ecc6299db9ec823/glob-0.3.0/src/lib.rs","byte_start":1057,"byte_end":1071,"line_start":23,"line_end":23,"column_start":1,"column_end":15}},{"value":"/","span":{"file_name":"/home/users/u6632448/.cargo/registry/src/github.com-1ecc6299db9ec823/glob-0.3.0/src/lib.rs","byte_start":1072,"byte_end":1075,"line_start":24,"line_end":24,"column_start":1,"column_end":4}},{"value":"/ To print all jpg files in `/media/` and all of its subdirectories.","span":{"file_name":"/home/users/u6632448/.cargo/registry/src/github.com-1ecc6299db9ec823/glob-0.3.0/src/lib.rs","byte_start":1076,"byte_end":1146,"line_start":25,"line_end":25,"column_start":1,"column_end":71}},{"value":"/","span":{"file_name":"/home/users/u6632448/.cargo/registry/src/github.com-1ecc6299db9ec823/glob-0.3.0/src/lib.rs","byte_start":1147,"byte_end":1150,"line_start":26,"line_end":26,"column_start":1,"column_end":4}},{"value":"/ ```rust,no_run","span":{"file_name":"/home/users/u6632448/.cargo/registry/src/github.com-1ecc6299db9ec823/glob-0.3.0/src/lib.rs","byte_start":1151,"byte_end":1169,"line_start":27,"line_end":27,"column_start":1,"column_end":19}},{"value":"/ use glob::glob;","span":{"file_name":"/home/users/u6632448/.cargo/registry/src/github.com-1ecc6299db9ec823/glob-0.3.0/src/lib.rs","byte_start":1170,"byte_end":1189,"line_start":28,"line_end":28,"column_start":1,"column_end":20}},{"value":"/","span":{"file_name":"/home/users/u6632448/.cargo/registry/src/github.com-1ecc6299db9ec823/glob-0.3.0/src/lib.rs","byte_start":1190,"byte_end":1193,"line_start":29,"line_end":29,"column_start":1,"column_end":4}},{"value":"/ for entry in glob(\"/media/**/*.jpg\").expect(\"Failed to read glob pattern\") {","span":{"file_name":"/home/users/u6632448/.cargo/registry/src/github.com-1ecc6299db9ec823/glob-0.3.0/src/lib.rs","byte_start":1194,"byte_end":1274,"line_start":30,"line_end":30,"column_start":1,"column_end":81}},{"value":"/     match entry {","span":{"file_name":"/home/users/u6632448/.cargo/registry/src/github.com-1ecc6299db9ec823/glob-0.3.0/src/lib.rs","byte_start":1275,"byte_end":1296,"line_start":31,"line_end":31,"column_start":1,"column_end":22}},{"value":"/         Ok(path) => println!(\"{:?}\", path.display()),","span":{"file_name":"/home/users/u6632448/.cargo/registry/src/github.com-1ecc6299db9ec823/glob-0.3.0/src/lib.rs","byte_start":1297,"byte_end":1354,"line_start":32,"line_end":32,"column_start":1,"column_end":58}},{"value":"/         Err(e) => println!(\"{:?}\", e),","span":{"file_name":"/home/users/u6632448/.cargo/registry/src/github.com-1ecc6299db9ec823/glob-0.3.0/src/lib.rs","byte_start":1355,"byte_end":1397,"line_start":33,"line_end":33,"column_start":1,"column_end":43}},{"value":"/     }","span":{"file_name":"/home/users/u6632448/.cargo/registry/src/github.com-1ecc6299db9ec823/glob-0.3.0/src/lib.rs","byte_start":1398,"byte_end":1407,"line_start":34,"line_end":34,"column_start":1,"column_end":10}},{"value":"/ }","span":{"file_name":"/home/users/u6632448/.cargo/registry/src/github.com-1ecc6299db9ec823/glob-0.3.0/src/lib.rs","byte_start":1408,"byte_end":1413,"line_start":35,"line_end":35,"column_start":1,"column_end":6}},{"value":"/ ```","span":{"file_name":"/home/users/u6632448/.cargo/registry/src/github.com-1ecc6299db9ec823/glob-0.3.0/src/lib.rs","byte_start":1414,"byte_end":1421,"line_start":36,"line_end":36,"column_start":1,"column_end":8}},{"value":"/","span":{"file_name":"/home/users/u6632448/.cargo/registry/src/github.com-1ecc6299db9ec823/glob-0.3.0/src/lib.rs","byte_start":1422,"byte_end":1425,"line_start":37,"line_end":37,"column_start":1,"column_end":4}},{"value":"/ To print all files containing the letter \"a\", case insensitive, in a `local`","span":{"file_name":"/home/users/u6632448/.cargo/registry/src/github.com-1ecc6299db9ec823/glob-0.3.0/src/lib.rs","byte_start":1426,"byte_end":1506,"line_start":38,"line_end":38,"column_start":1,"column_end":81}},{"value":"/ directory relative to the current working directory. This ignores errors","span":{"file_name":"/home/users/u6632448/.cargo/registry/src/github.com-1ecc6299db9ec823/glob-0.3.0/src/lib.rs","byte_start":1507,"byte_end":1583,"line_start":39,"line_end":39,"column_start":1,"column_end":77}},{"value":"/ instead of printing them.","span":{"file_name":"/home/users/u6632448/.cargo/registry/src/github.com-1ecc6299db9ec823/glob-0.3.0/src/lib.rs","byte_start":1584,"byte_end":1613,"line_start":40,"line_end":40,"column_start":1,"column_end":30}},{"value":"/","span":{"file_name":"/home/users/u6632448/.cargo/registry/src/github.com-1ecc6299db9ec823/glob-0.3.0/src/lib.rs","byte_start":1614,"byte_end":1617,"line_start":41,"line_end":41,"column_start":1,"column_end":4}},{"value":"/ ```rust,no_run","span":{"file_name":"/home/users/u6632448/.cargo/registry/src/github.com-1ecc6299db9ec823/glob-0.3.0/src/lib.rs","byte_start":1618,"byte_end":1636,"line_start":42,"line_end":42,"column_start":1,"column_end":19}},{"value":"/ use glob::glob_with;","span":{"file_name":"/home/users/u6632448/.cargo/registry/src/github.com-1ecc6299db9ec823/glob-0.3.0/src/lib.rs","byte_start":1637,"byte_end":1661,"line_start":43,"line_end":43,"column_start":1,"column_end":25}},{"value":"/ use glob::MatchOptions;","span":{"file_name":"/home/users/u6632448/.cargo/registry/src/github.com-1ecc6299db9ec823/glob-0.3.0/src/lib.rs","byte_start":1662,"byte_end":1689,"line_start":44,"line_end":44,"column_start":1,"column_end":28}},{"value":"/","span":{"file_name":"/home/users/u6632448/.cargo/registry/src/github.com-1ecc6299db9ec823/glob-0.3.0/src/lib.rs","byte_start":1690,"byte_end":1693,"line_start":45,"line_end":45,"column_start":1,"column_end":4}},{"value":"/ let options = MatchOptions {","span":{"file_name":"/home/users/u6632448/.cargo/registry/src/github.com-1ecc6299db9ec823/glob-0.3.0/src/lib.rs","byte_start":1694,"byte_end":1726,"line_start":46,"line_end":46,"column_start":1,"column_end":33}},{"value":"/     case_sensitive: false,","span":{"file_name":"/home/users/u6632448/.cargo/registry/src/github.com-1ecc6299db9ec823/glob-0.3.0/src/lib.rs","byte_start":1727,"byte_end":1757,"line_start":47,"line_end":47,"column_start":1,"column_end":31}},{"value":"/     require_literal_separator: false,","span":{"file_name":"/home/users/u6632448/.cargo/registry/src/github.com-1ecc6299db9ec823/glob-0.3.0/src/lib.rs","byte_start":1758,"byte_end":1799,"line_start":48,"line_end":48,"column_start":1,"column_end":42}},{"value":"/     require_literal_leading_dot: false,","span":{"file_name":"/home/users/u6632448/.cargo/registry/src/github.com-1ecc6299db9ec823/glob-0.3.0/src/lib.rs","byte_start":1800,"byte_end":1843,"line_start":49,"line_end":49,"column_start":1,"column_end":44}},{"value":"/ };","span":{"file_name":"/home/users/u6632448/.cargo/registry/src/github.com-1ecc6299db9ec823/glob-0.3.0/src/lib.rs","byte_start":1844,"byte_end":1850,"line_start":50,"line_end":50,"column_start":1,"column_end":7}},{"value":"/ for entry in glob_with(\"local/*a*\", options).unwrap() {","span":{"file_name":"/home/users/u6632448/.cargo/registry/src/github.com-1ecc6299db9ec823/glob-0.3.0/src/lib.rs","byte_start":1851,"byte_end":1910,"line_start":51,"line_end":51,"column_start":1,"column_end":60}},{"value":"/     if let Ok(path) = entry {","span":{"file_name":"/home/users/u6632448/.cargo/registry/src/github.com-1ecc6299db9ec823/glob-0.3.0/src/lib.rs","byte_start":1911,"byte_end":1944,"line_start":52,"line_end":52,"column_start":1,"column_end":34}},{"value":"/         println!(\"{:?}\", path.display())","span":{"file_name":"/home/users/u6632448/.cargo/registry/src/github.com-1ecc6299db9ec823/glob-0.3.0/src/lib.rs","byte_start":1945,"byte_end":1989,"line_start":53,"line_end":53,"column_start":1,"column_end":45}},{"value":"/     }","span":{"file_name":"/home/users/u6632448/.cargo/registry/src/github.com-1ecc6299db9ec823/glob-0.3.0/src/lib.rs","byte_start":1990,"byte_end":1999,"line_start":54,"line_end":54,"column_start":1,"column_end":10}},{"value":"/ }","span":{"file_name":"/home/users/u6632448/.cargo/registry/src/github.com-1ecc6299db9ec823/glob-0.3.0/src/lib.rs","byte_start":2000,"byte_end":2005,"line_start":55,"line_end":55,"column_start":1,"column_end":6}},{"value":"/ ```","span":{"file_name":"/home/users/u6632448/.cargo/registry/src/github.com-1ecc6299db9ec823/glob-0.3.0/src/lib.rs","byte_start":2006,"byte_end":2013,"line_start":56,"line_end":56,"column_start":1,"column_end":8}},{"value":"deny(missing_docs)","span":{"file_name":"/home/users/u6632448/.cargo/registry/src/github.com-1ecc6299db9ec823/glob-0.3.0/src/lib.rs","byte_start":2223,"byte_end":2245,"line_start":63,"line_end":63,"column_start":1,"column_end":23}}]},{"kind":"Struct","id":{"krate":0,"index":70},"span":{"file_name":"/home/users/u6632448/.cargo/registry/src/github.com-1ecc6299db9ec823/glob-0.3.0/src/lib.rs","byte_start":3102,"byte_end":3107,"line_start":88,"line_end":88,"column_start":12,"column_end":17},"name":"Paths","qualname":"::Paths","value":"Paths {  }","parent":null,"children":[{"krate":0,"index":71},{"krate":0,"index":72},{"krate":0,"index":73},{"krate":0,"index":74},{"krate":0,"index":75}],"decl_id":null,"docs":" An iterator that yields `Path`s from the filesystem that match a particular\n pattern.","sig":null,"attributes":[{"value":"/ An iterator that yields `Path`s from the filesystem that match a particular","span":{"file_name":"/home/users/u6632448/.cargo/registry/src/github.com-1ecc6299db9ec823/glob-0.3.0/src/lib.rs","byte_start":2679,"byte_end":2758,"line_start":79,"line_end":79,"column_start":1,"column_end":80}},{"value":"/ pattern.","span":{"file_name":"/home/users/u6632448/.cargo/registry/src/github.com-1ecc6299db9ec823/glob-0.3.0/src/lib.rs","byte_start":2759,"byte_end":2771,"line_start":80,"line_end":80,"column_start":1,"column_end":13}},{"value":"/","span":{"file_name":"/home/users/u6632448/.cargo/registry/src/github.com-1ecc6299db9ec823/glob-0.3.0/src/lib.rs","byte_start":2772,"byte_end":2775,"line_start":81,"line_end":81,"column_start":1,"column_end":4}},{"value":"/ Note that it yields `GlobResult` in order to report any `IoErrors` that may","span":{"file_name":"/home/users/u6632448/.cargo/registry/src/github.com-1ecc6299db9ec823/glob-0.3.0/src/lib.rs","byte_start":2776,"byte_end":2855,"line_start":82,"line_end":82,"column_start":1,"column_end":80}},{"value":"/ arise during iteration. If a directory matches but is unreadable,","span":{"file_name":"/home/users/u6632448/.cargo/registry/src/github.com-1ecc6299db9ec823/glob-0.3.0/src/lib.rs","byte_start":2856,"byte_end":2925,"line_start":83,"line_end":83,"column_start":1,"column_end":70}},{"value":"/ thereby preventing its contents from being checked for matches, a","span":{"file_name":"/home/users/u6632448/.cargo/registry/src/github.com-1ecc6299db9ec823/glob-0.3.0/src/lib.rs","byte_start":2926,"byte_end":2995,"line_start":84,"line_end":84,"column_start":1,"column_end":70}},{"value":"/ `GlobError` is returned to express this.","span":{"file_name":"/home/users/u6632448/.cargo/registry/src/github.com-1ecc6299db9ec823/glob-0.3.0/src/lib.rs","byte_start":2996,"byte_end":3040,"line_start":85,"line_end":85,"column_start":1,"column_end":45}},{"value":"/","span":{"file_name":"/home/users/u6632448/.cargo/registry/src/github.com-1ecc6299db9ec823/glob-0.3.0/src/lib.rs","byte_start":3041,"byte_end":3044,"line_start":86,"line_end":86,"column_start":1,"column_end":4}},{"value":"/ See the `glob` function for more details.","span":{"file_name":"/home/users/u6632448/.cargo/registry/src/github.com-1ecc6299db9ec823/glob-0.3.0/src/lib.rs","byte_start":3045,"byte_end":3090,"line_start":87,"line_end":87,"column_start":1,"column_end":46}}]},{"kind":"Function","id":{"krate":0,"index":76},"span":{"file_name":"/home/users/u6632448/.cargo/registry/src/github.com-1ecc6299db9ec823/glob-0.3.0/src/lib.rs","byte_start":5207,"byte_end":5211,"line_start":153,"line_end":153,"column_start":8,"column_end":12},"name":"glob","qualname":"::glob","value":"pub fn glob(&str) -> Result<Paths, PatternError>","parent":null,"children":[],"decl_id":null,"docs":" Return an iterator that produces all the `Path`s that match the given\n pattern using default match options, which may be absolute or relative to\n the current working directory.","sig":null,"attributes":[{"value":"/ Return an iterator that produces all the `Path`s that match the given","span":{"file_name":"/home/users/u6632448/.cargo/registry/src/github.com-1ecc6299db9ec823/glob-0.3.0/src/lib.rs","byte_start":3275,"byte_end":3348,"line_start":96,"line_end":96,"column_start":1,"column_end":74}},{"value":"/ pattern using default match options, which may be absolute or relative to","span":{"file_name":"/home/users/u6632448/.cargo/registry/src/github.com-1ecc6299db9ec823/glob-0.3.0/src/lib.rs","byte_start":3349,"byte_end":3426,"line_start":97,"line_end":97,"column_start":1,"column_end":78}},{"value":"/ the current working directory.","span":{"file_name":"/home/users/u6632448/.cargo/registry/src/github.com-1ecc6299db9ec823/glob-0.3.0/src/lib.rs","byte_start":3427,"byte_end":3461,"line_start":98,"line_end":98,"column_start":1,"column_end":35}},{"value":"/","span":{"file_name":"/home/users/u6632448/.cargo/registry/src/github.com-1ecc6299db9ec823/glob-0.3.0/src/lib.rs","byte_start":3462,"byte_end":3465,"line_start":99,"line_end":99,"column_start":1,"column_end":4}},{"value":"/ This may return an error if the pattern is invalid.","span":{"file_name":"/home/users/u6632448/.cargo/registry/src/github.com-1ecc6299db9ec823/glob-0.3.0/src/lib.rs","byte_start":3466,"byte_end":3521,"line_start":100,"line_end":100,"column_start":1,"column_end":56}},{"value":"/","span":{"file_name":"/home/users/u6632448/.cargo/registry/src/github.com-1ecc6299db9ec823/glob-0.3.0/src/lib.rs","byte_start":3522,"byte_end":3525,"line_start":101,"line_end":101,"column_start":1,"column_end":4}},{"value":"/ This method uses the default match options and is equivalent to calling","span":{"file_name":"/home/users/u6632448/.cargo/registry/src/github.com-1ecc6299db9ec823/glob-0.3.0/src/lib.rs","byte_start":3526,"byte_end":3601,"line_start":102,"line_end":102,"column_start":1,"column_end":76}},{"value":"/ `glob_with(pattern, MatchOptions::new())`. Use `glob_with` directly if you","span":{"file_name":"/home/users/u6632448/.cargo/registry/src/github.com-1ecc6299db9ec823/glob-0.3.0/src/lib.rs","byte_start":3602,"byte_end":3680,"line_start":103,"line_end":103,"column_start":1,"column_end":79}},{"value":"/ want to use non-default match options.","span":{"file_name":"/home/users/u6632448/.cargo/registry/src/github.com-1ecc6299db9ec823/glob-0.3.0/src/lib.rs","byte_start":3681,"byte_end":3723,"line_start":104,"line_end":104,"column_start":1,"column_end":43}},{"value":"/","span":{"file_name":"/home/users/u6632448/.cargo/registry/src/github.com-1ecc6299db9ec823/glob-0.3.0/src/lib.rs","byte_start":3724,"byte_end":3727,"line_start":105,"line_end":105,"column_start":1,"column_end":4}},{"value":"/ When iterating, each result is a `GlobResult` which expresses the","span":{"file_name":"/home/users/u6632448/.cargo/registry/src/github.com-1ecc6299db9ec823/glob-0.3.0/src/lib.rs","byte_start":3728,"byte_end":3797,"line_start":106,"line_end":106,"column_start":1,"column_end":70}},{"value":"/ possibility that there was an `IoError` when attempting to read the contents","span":{"file_name":"/home/users/u6632448/.cargo/registry/src/github.com-1ecc6299db9ec823/glob-0.3.0/src/lib.rs","byte_start":3798,"byte_end":3878,"line_start":107,"line_end":107,"column_start":1,"column_end":81}},{"value":"/ of the matched path.  In other words, each item returned by the iterator","span":{"file_name":"/home/users/u6632448/.cargo/registry/src/github.com-1ecc6299db9ec823/glob-0.3.0/src/lib.rs","byte_start":3879,"byte_end":3955,"line_start":108,"line_end":108,"column_start":1,"column_end":77}},{"value":"/ will either be an `Ok(Path)` if the path matched, or an `Err(GlobError)` if","span":{"file_name":"/home/users/u6632448/.cargo/registry/src/github.com-1ecc6299db9ec823/glob-0.3.0/src/lib.rs","byte_start":3956,"byte_end":4035,"line_start":109,"line_end":109,"column_start":1,"column_end":80}},{"value":"/ the path (partially) matched _but_ its contents could not be read in order","span":{"file_name":"/home/users/u6632448/.cargo/registry/src/github.com-1ecc6299db9ec823/glob-0.3.0/src/lib.rs","byte_start":4036,"byte_end":4114,"line_start":110,"line_end":110,"column_start":1,"column_end":79}},{"value":"/ to determine if its contents matched.","span":{"file_name":"/home/users/u6632448/.cargo/registry/src/github.com-1ecc6299db9ec823/glob-0.3.0/src/lib.rs","byte_start":4115,"byte_end":4156,"line_start":111,"line_end":111,"column_start":1,"column_end":42}},{"value":"/","span":{"file_name":"/home/users/u6632448/.cargo/registry/src/github.com-1ecc6299db9ec823/glob-0.3.0/src/lib.rs","byte_start":4157,"byte_end":4160,"line_start":112,"line_end":112,"column_start":1,"column_end":4}},{"value":"/ See the `Paths` documentation for more information.","span":{"file_name":"/home/users/u6632448/.cargo/registry/src/github.com-1ecc6299db9ec823/glob-0.3.0/src/lib.rs","byte_start":4161,"byte_end":4216,"line_start":113,"line_end":113,"column_start":1,"column_end":56}},{"value":"/","span":{"file_name":"/home/users/u6632448/.cargo/registry/src/github.com-1ecc6299db9ec823/glob-0.3.0/src/lib.rs","byte_start":4217,"byte_end":4220,"line_start":114,"line_end":114,"column_start":1,"column_end":4}},{"value":"/ # Examples","span":{"file_name":"/home/users/u6632448/.cargo/registry/src/github.com-1ecc6299db9ec823/glob-0.3.0/src/lib.rs","byte_start":4221,"byte_end":4235,"line_start":115,"line_end":115,"column_start":1,"column_end":15}},{"value":"/","span":{"file_name":"/home/users/u6632448/.cargo/registry/src/github.com-1ecc6299db9ec823/glob-0.3.0/src/lib.rs","byte_start":4236,"byte_end":4239,"line_start":116,"line_end":116,"column_start":1,"column_end":4}},{"value":"/ Consider a directory `/media/pictures` containing only the files","span":{"file_name":"/home/users/u6632448/.cargo/registry/src/github.com-1ecc6299db9ec823/glob-0.3.0/src/lib.rs","byte_start":4240,"byte_end":4308,"line_start":117,"line_end":117,"column_start":1,"column_end":69}},{"value":"/ `kittens.jpg`, `puppies.jpg` and `hamsters.gif`:","span":{"file_name":"/home/users/u6632448/.cargo/registry/src/github.com-1ecc6299db9ec823/glob-0.3.0/src/lib.rs","byte_start":4309,"byte_end":4361,"line_start":118,"line_end":118,"column_start":1,"column_end":53}},{"value":"/","span":{"file_name":"/home/users/u6632448/.cargo/registry/src/github.com-1ecc6299db9ec823/glob-0.3.0/src/lib.rs","byte_start":4362,"byte_end":4365,"line_start":119,"line_end":119,"column_start":1,"column_end":4}},{"value":"/ ```rust,no_run","span":{"file_name":"/home/users/u6632448/.cargo/registry/src/github.com-1ecc6299db9ec823/glob-0.3.0/src/lib.rs","byte_start":4366,"byte_end":4384,"line_start":120,"line_end":120,"column_start":1,"column_end":19}},{"value":"/ use glob::glob;","span":{"file_name":"/home/users/u6632448/.cargo/registry/src/github.com-1ecc6299db9ec823/glob-0.3.0/src/lib.rs","byte_start":4385,"byte_end":4404,"line_start":121,"line_end":121,"column_start":1,"column_end":20}},{"value":"/","span":{"file_name":"/home/users/u6632448/.cargo/registry/src/github.com-1ecc6299db9ec823/glob-0.3.0/src/lib.rs","byte_start":4405,"byte_end":4408,"line_start":122,"line_end":122,"column_start":1,"column_end":4}},{"value":"/ for entry in glob(\"/media/pictures/*.jpg\").unwrap() {","span":{"file_name":"/home/users/u6632448/.cargo/registry/src/github.com-1ecc6299db9ec823/glob-0.3.0/src/lib.rs","byte_start":4409,"byte_end":4466,"line_start":123,"line_end":123,"column_start":1,"column_end":58}},{"value":"/     match entry {","span":{"file_name":"/home/users/u6632448/.cargo/registry/src/github.com-1ecc6299db9ec823/glob-0.3.0/src/lib.rs","byte_start":4467,"byte_end":4488,"line_start":124,"line_end":124,"column_start":1,"column_end":22}},{"value":"/         Ok(path) => println!(\"{:?}\", path.display()),","span":{"file_name":"/home/users/u6632448/.cargo/registry/src/github.com-1ecc6299db9ec823/glob-0.3.0/src/lib.rs","byte_start":4489,"byte_end":4546,"line_start":125,"line_end":125,"column_start":1,"column_end":58}},{"value":"/","span":{"file_name":"/home/users/u6632448/.cargo/registry/src/github.com-1ecc6299db9ec823/glob-0.3.0/src/lib.rs","byte_start":4547,"byte_end":4550,"line_start":126,"line_end":126,"column_start":1,"column_end":4}},{"value":"/         // if the path matched but was unreadable,","span":{"file_name":"/home/users/u6632448/.cargo/registry/src/github.com-1ecc6299db9ec823/glob-0.3.0/src/lib.rs","byte_start":4551,"byte_end":4605,"line_start":127,"line_end":127,"column_start":1,"column_end":55}},{"value":"/         // thereby preventing its contents from matching","span":{"file_name":"/home/users/u6632448/.cargo/registry/src/github.com-1ecc6299db9ec823/glob-0.3.0/src/lib.rs","byte_start":4606,"byte_end":4666,"line_start":128,"line_end":128,"column_start":1,"column_end":61}},{"value":"/         Err(e) => println!(\"{:?}\", e),","span":{"file_name":"/home/users/u6632448/.cargo/registry/src/github.com-1ecc6299db9ec823/glob-0.3.0/src/lib.rs","byte_start":4667,"byte_end":4709,"line_start":129,"line_end":129,"column_start":1,"column_end":43}},{"value":"/     }","span":{"file_name":"/home/users/u6632448/.cargo/registry/src/github.com-1ecc6299db9ec823/glob-0.3.0/src/lib.rs","byte_start":4710,"byte_end":4719,"line_start":130,"line_end":130,"column_start":1,"column_end":10}},{"value":"/ }","span":{"file_name":"/home/users/u6632448/.cargo/registry/src/github.com-1ecc6299db9ec823/glob-0.3.0/src/lib.rs","byte_start":4720,"byte_end":4725,"line_start":131,"line_end":131,"column_start":1,"column_end":6}},{"value":"/ ```","span":{"file_name":"/home/users/u6632448/.cargo/registry/src/github.com-1ecc6299db9ec823/glob-0.3.0/src/lib.rs","byte_start":4726,"byte_end":4733,"line_start":132,"line_end":132,"column_start":1,"column_end":8}},{"value":"/","span":{"file_name":"/home/users/u6632448/.cargo/registry/src/github.com-1ecc6299db9ec823/glob-0.3.0/src/lib.rs","byte_start":4734,"byte_end":4737,"line_start":133,"line_end":133,"column_start":1,"column_end":4}},{"value":"/ The above code will print:","span":{"file_name":"/home/users/u6632448/.cargo/registry/src/github.com-1ecc6299db9ec823/glob-0.3.0/src/lib.rs","byte_start":4738,"byte_end":4768,"line_start":134,"line_end":134,"column_start":1,"column_end":31}},{"value":"/","span":{"file_name":"/home/users/u6632448/.cargo/registry/src/github.com-1ecc6299db9ec823/glob-0.3.0/src/lib.rs","byte_start":4769,"byte_end":4772,"line_start":135,"line_end":135,"column_start":1,"column_end":4}},{"value":"/ ```ignore","span":{"file_name":"/home/users/u6632448/.cargo/registry/src/github.com-1ecc6299db9ec823/glob-0.3.0/src/lib.rs","byte_start":4773,"byte_end":4786,"line_start":136,"line_end":136,"column_start":1,"column_end":14}},{"value":"/ /media/pictures/kittens.jpg","span":{"file_name":"/home/users/u6632448/.cargo/registry/src/github.com-1ecc6299db9ec823/glob-0.3.0/src/lib.rs","byte_start":4787,"byte_end":4818,"line_start":137,"line_end":137,"column_start":1,"column_end":32}},{"value":"/ /media/pictures/puppies.jpg","span":{"file_name":"/home/users/u6632448/.cargo/registry/src/github.com-1ecc6299db9ec823/glob-0.3.0/src/lib.rs","byte_start":4819,"byte_end":4850,"line_start":138,"line_end":138,"column_start":1,"column_end":32}},{"value":"/ ```","span":{"file_name":"/home/users/u6632448/.cargo/registry/src/github.com-1ecc6299db9ec823/glob-0.3.0/src/lib.rs","byte_start":4851,"byte_end":4858,"line_start":139,"line_end":139,"column_start":1,"column_end":8}},{"value":"/","span":{"file_name":"/home/users/u6632448/.cargo/registry/src/github.com-1ecc6299db9ec823/glob-0.3.0/src/lib.rs","byte_start":4859,"byte_end":4862,"line_start":140,"line_end":140,"column_start":1,"column_end":4}},{"value":"/ If you want to ignore unreadable paths, you can use something like","span":{"file_name":"/home/users/u6632448/.cargo/registry/src/github.com-1ecc6299db9ec823/glob-0.3.0/src/lib.rs","byte_start":4863,"byte_end":4933,"line_start":141,"line_end":141,"column_start":1,"column_end":71}},{"value":"/ `filter_map`:","span":{"file_name":"/home/users/u6632448/.cargo/registry/src/github.com-1ecc6299db9ec823/glob-0.3.0/src/lib.rs","byte_start":4934,"byte_end":4951,"line_start":142,"line_end":142,"column_start":1,"column_end":18}},{"value":"/","span":{"file_name":"/home/users/u6632448/.cargo/registry/src/github.com-1ecc6299db9ec823/glob-0.3.0/src/lib.rs","byte_start":4952,"byte_end":4955,"line_start":143,"line_end":143,"column_start":1,"column_end":4}},{"value":"/ ```rust","span":{"file_name":"/home/users/u6632448/.cargo/registry/src/github.com-1ecc6299db9ec823/glob-0.3.0/src/lib.rs","byte_start":4956,"byte_end":4967,"line_start":144,"line_end":144,"column_start":1,"column_end":12}},{"value":"/ use glob::glob;","span":{"file_name":"/home/users/u6632448/.cargo/registry/src/github.com-1ecc6299db9ec823/glob-0.3.0/src/lib.rs","byte_start":4968,"byte_end":4987,"line_start":145,"line_end":145,"column_start":1,"column_end":20}},{"value":"/ use std::result::Result;","span":{"file_name":"/home/users/u6632448/.cargo/registry/src/github.com-1ecc6299db9ec823/glob-0.3.0/src/lib.rs","byte_start":4988,"byte_end":5016,"line_start":146,"line_end":146,"column_start":1,"column_end":29}},{"value":"/","span":{"file_name":"/home/users/u6632448/.cargo/registry/src/github.com-1ecc6299db9ec823/glob-0.3.0/src/lib.rs","byte_start":5017,"byte_end":5020,"line_start":147,"line_end":147,"column_start":1,"column_end":4}},{"value":"/ for path in glob(\"/media/pictures/*.jpg\").unwrap().filter_map(Result::ok) {","span":{"file_name":"/home/users/u6632448/.cargo/registry/src/github.com-1ecc6299db9ec823/glob-0.3.0/src/lib.rs","byte_start":5021,"byte_end":5100,"line_start":148,"line_end":148,"column_start":1,"column_end":80}},{"value":"/     println!(\"{}\", path.display());","span":{"file_name":"/home/users/u6632448/.cargo/registry/src/github.com-1ecc6299db9ec823/glob-0.3.0/src/lib.rs","byte_start":5101,"byte_end":5140,"line_start":149,"line_end":149,"column_start":1,"column_end":40}},{"value":"/ }","span":{"file_name":"/home/users/u6632448/.cargo/registry/src/github.com-1ecc6299db9ec823/glob-0.3.0/src/lib.rs","byte_start":5141,"byte_end":5146,"line_start":150,"line_end":150,"column_start":1,"column_end":6}},{"value":"/ ```","span":{"file_name":"/home/users/u6632448/.cargo/registry/src/github.com-1ecc6299db9ec823/glob-0.3.0/src/lib.rs","byte_start":5147,"byte_end":5154,"line_start":151,"line_end":151,"column_start":1,"column_end":8}},{"value":"/ Paths are yielded in alphabetical order.","span":{"file_name":"/home/users/u6632448/.cargo/registry/src/github.com-1ecc6299db9ec823/glob-0.3.0/src/lib.rs","byte_start":5155,"byte_end":5199,"line_start":152,"line_end":152,"column_start":1,"column_end":45}}]},{"kind":"Function","id":{"krate":0,"index":77},"span":{"file_name":"/home/users/u6632448/.cargo/registry/src/github.com-1ecc6299db9ec823/glob-0.3.0/src/lib.rs","byte_start":5928,"byte_end":5937,"line_start":170,"line_end":170,"column_start":8,"column_end":17},"name":"glob_with","qualname":"::glob_with","value":"pub fn glob_with(&str, MatchOptions) -> Result<Paths, PatternError>","parent":null,"children":[],"decl_id":null,"docs":" Return an iterator that produces all the `Path`s that match the given\n pattern using the specified match options, which may be absolute or relative\n to the current working directory.","sig":null,"attributes":[{"value":"/ Return an iterator that produces all the `Path`s that match the given","span":{"file_name":"/home/users/u6632448/.cargo/registry/src/github.com-1ecc6299db9ec823/glob-0.3.0/src/lib.rs","byte_start":5307,"byte_end":5380,"line_start":157,"line_end":157,"column_start":1,"column_end":74}},{"value":"/ pattern using the specified match options, which may be absolute or relative","span":{"file_name":"/home/users/u6632448/.cargo/registry/src/github.com-1ecc6299db9ec823/glob-0.3.0/src/lib.rs","byte_start":5381,"byte_end":5461,"line_start":158,"line_end":158,"column_start":1,"column_end":81}},{"value":"/ to the current working directory.","span":{"file_name":"/home/users/u6632448/.cargo/registry/src/github.com-1ecc6299db9ec823/glob-0.3.0/src/lib.rs","byte_start":5462,"byte_end":5499,"line_start":159,"line_end":159,"column_start":1,"column_end":38}},{"value":"/","span":{"file_name":"/home/users/u6632448/.cargo/registry/src/github.com-1ecc6299db9ec823/glob-0.3.0/src/lib.rs","byte_start":5500,"byte_end":5503,"line_start":160,"line_end":160,"column_start":1,"column_end":4}},{"value":"/ This may return an error if the pattern is invalid.","span":{"file_name":"/home/users/u6632448/.cargo/registry/src/github.com-1ecc6299db9ec823/glob-0.3.0/src/lib.rs","byte_start":5504,"byte_end":5559,"line_start":161,"line_end":161,"column_start":1,"column_end":56}},{"value":"/","span":{"file_name":"/home/users/u6632448/.cargo/registry/src/github.com-1ecc6299db9ec823/glob-0.3.0/src/lib.rs","byte_start":5560,"byte_end":5563,"line_start":162,"line_end":162,"column_start":1,"column_end":4}},{"value":"/ This function accepts Unix shell style patterns as described by","span":{"file_name":"/home/users/u6632448/.cargo/registry/src/github.com-1ecc6299db9ec823/glob-0.3.0/src/lib.rs","byte_start":5564,"byte_end":5631,"line_start":163,"line_end":163,"column_start":1,"column_end":68}},{"value":"/ `Pattern::new(..)`.  The options given are passed through unchanged to","span":{"file_name":"/home/users/u6632448/.cargo/registry/src/github.com-1ecc6299db9ec823/glob-0.3.0/src/lib.rs","byte_start":5632,"byte_end":5706,"line_start":164,"line_end":164,"column_start":1,"column_end":75}},{"value":"/ `Pattern::matches_with(..)` with the exception that","span":{"file_name":"/home/users/u6632448/.cargo/registry/src/github.com-1ecc6299db9ec823/glob-0.3.0/src/lib.rs","byte_start":5707,"byte_end":5762,"line_start":165,"line_end":165,"column_start":1,"column_end":56}},{"value":"/ `require_literal_separator` is always set to `true` regardless of the value","span":{"file_name":"/home/users/u6632448/.cargo/registry/src/github.com-1ecc6299db9ec823/glob-0.3.0/src/lib.rs","byte_start":5763,"byte_end":5842,"line_start":166,"line_end":166,"column_start":1,"column_end":80}},{"value":"/ passed to this function.","span":{"file_name":"/home/users/u6632448/.cargo/registry/src/github.com-1ecc6299db9ec823/glob-0.3.0/src/lib.rs","byte_start":5843,"byte_end":5871,"line_start":167,"line_end":167,"column_start":1,"column_end":29}},{"value":"/","span":{"file_name":"/home/users/u6632448/.cargo/registry/src/github.com-1ecc6299db9ec823/glob-0.3.0/src/lib.rs","byte_start":5872,"byte_end":5875,"line_start":168,"line_end":168,"column_start":1,"column_end":4}},{"value":"/ Paths are yielded in alphabetical order.","span":{"file_name":"/home/users/u6632448/.cargo/registry/src/github.com-1ecc6299db9ec823/glob-0.3.0/src/lib.rs","byte_start":5876,"byte_end":5920,"line_start":169,"line_end":169,"column_start":1,"column_end":45}}]},{"kind":"Struct","id":{"krate":0,"index":136},"span":{"file_name":"/home/users/u6632448/.cargo/registry/src/github.com-1ecc6299db9ec823/glob-0.3.0/src/lib.rs","byte_start":8887,"byte_end":8896,"line_start":267,"line_end":267,"column_start":12,"column_end":21},"name":"GlobError","qualname":"::GlobError","value":"GlobError {  }","parent":null,"children":[{"krate":0,"index":137},{"krate":0,"index":138}],"decl_id":null,"docs":" A glob iteration error.","sig":null,"attributes":[{"value":"/ A glob iteration error.","span":{"file_name":"/home/users/u6632448/.cargo/registry/src/github.com-1ecc6299db9ec823/glob-0.3.0/src/lib.rs","byte_start":8617,"byte_end":8644,"line_start":261,"line_end":261,"column_start":1,"column_end":28}},{"value":"/","span":{"file_name":"/home/users/u6632448/.cargo/registry/src/github.com-1ecc6299db9ec823/glob-0.3.0/src/lib.rs","byte_start":8645,"byte_end":8648,"line_start":262,"line_end":262,"column_start":1,"column_end":4}},{"value":"/ This is typically returned when a particular path cannot be read","span":{"file_name":"/home/users/u6632448/.cargo/registry/src/github.com-1ecc6299db9ec823/glob-0.3.0/src/lib.rs","byte_start":8649,"byte_end":8717,"line_start":263,"line_end":263,"column_start":1,"column_end":69}},{"value":"/ to determine if its contents match the glob pattern. This is possible","span":{"file_name":"/home/users/u6632448/.cargo/registry/src/github.com-1ecc6299db9ec823/glob-0.3.0/src/lib.rs","byte_start":8718,"byte_end":8791,"line_start":264,"line_end":264,"column_start":1,"column_end":74}},{"value":"/ if the program lacks the appropriate permissions, for example.","span":{"file_name":"/home/users/u6632448/.cargo/registry/src/github.com-1ecc6299db9ec823/glob-0.3.0/src/lib.rs","byte_start":8792,"byte_end":8858,"line_start":265,"line_end":265,"column_start":1,"column_end":67}}]},{"kind":"Method","id":{"krate":0,"index":83},"span":{"file_name":"/home/users/u6632448/.cargo/registry/src/github.com-1ecc6299db9ec823/glob-0.3.0/src/lib.rs","byte_start":9019,"byte_end":9023,"line_start":274,"line_end":274,"column_start":12,"column_end":16},"name":"path","qualname":"<GlobError>::path","value":"pub fn path(&Self) -> &Path","parent":null,"children":[],"decl_id":null,"docs":" The Path that the error corresponds to.\n","sig":null,"attributes":[{"value":"/ The Path that the error corresponds to.","span":{"file_name":"/home/users/u6632448/.cargo/registry/src/github.com-1ecc6299db9ec823/glob-0.3.0/src/lib.rs","byte_start":8964,"byte_end":9007,"line_start":273,"line_end":273,"column_start":5,"column_end":48}}]},{"kind":"Method","id":{"krate":0,"index":84},"span":{"file_name":"/home/users/u6632448/.cargo/registry/src/github.com-1ecc6299db9ec823/glob-0.3.0/src/lib.rs","byte_start":9110,"byte_end":9115,"line_start":279,"line_end":279,"column_start":12,"column_end":17},"name":"error","qualname":"<GlobError>::error","value":"pub fn error(&Self) -> &io::Error","parent":null,"children":[],"decl_id":null,"docs":" The error in question.\n","sig":null,"attributes":[{"value":"/ The error in question.","span":{"file_name":"/home/users/u6632448/.cargo/registry/src/github.com-1ecc6299db9ec823/glob-0.3.0/src/lib.rs","byte_start":9072,"byte_end":9098,"line_start":278,"line_end":278,"column_start":5,"column_end":31}}]},{"kind":"Method","id":{"krate":0,"index":85},"span":{"file_name":"/home/users/u6632448/.cargo/registry/src/github.com-1ecc6299db9ec823/glob-0.3.0/src/lib.rs","byte_start":9243,"byte_end":9253,"line_start":284,"line_end":284,"column_start":12,"column_end":22},"name":"into_error","qualname":"<GlobError>::into_error","value":"pub fn into_error(Self) -> io::Error","parent":null,"children":[],"decl_id":null,"docs":" Consumes self, returning the _raw_ underlying `io::Error`\n","sig":null,"attributes":[{"value":"/ Consumes self, returning the _raw_ underlying `io::Error`","span":{"file_name":"/home/users/u6632448/.cargo/registry/src/github.com-1ecc6299db9ec823/glob-0.3.0/src/lib.rs","byte_start":9170,"byte_end":9231,"line_start":283,"line_end":283,"column_start":5,"column_end":66}}]},{"kind":"Type","id":{"krate":0,"index":93},"span":{"file_name":"/home/users/u6632448/.cargo/registry/src/github.com-1ecc6299db9ec823/glob-0.3.0/src/lib.rs","byte_start":10021,"byte_end":10031,"line_start":318,"line_end":318,"column_start":10,"column_end":20},"name":"GlobResult","qualname":"::GlobResult","value":"Result<PathBuf, GlobError>","parent":null,"children":[],"decl_id":null,"docs":" An alias for a glob iteration result.","sig":null,"attributes":[{"value":"/ An alias for a glob iteration result.","span":{"file_name":"/home/users/u6632448/.cargo/registry/src/github.com-1ecc6299db9ec823/glob-0.3.0/src/lib.rs","byte_start":9834,"byte_end":9875,"line_start":314,"line_end":314,"column_start":1,"column_end":42}},{"value":"/","span":{"file_name":"/home/users/u6632448/.cargo/registry/src/github.com-1ecc6299db9ec823/glob-0.3.0/src/lib.rs","byte_start":9876,"byte_end":9879,"line_start":315,"line_end":315,"column_start":1,"column_end":4}},{"value":"/ This represents either a matched path or a glob iteration error,","span":{"file_name":"/home/users/u6632448/.cargo/registry/src/github.com-1ecc6299db9ec823/glob-0.3.0/src/lib.rs","byte_start":9880,"byte_end":9948,"line_start":316,"line_end":316,"column_start":1,"column_end":69}},{"value":"/ such as failing to read a particular directory's contents.","span":{"file_name":"/home/users/u6632448/.cargo/registry/src/github.com-1ecc6299db9ec823/glob-0.3.0/src/lib.rs","byte_start":9949,"byte_end":10011,"line_start":317,"line_end":317,"column_start":1,"column_end":63}}]},{"kind":"Struct","id":{"krate":0,"index":141},"span":{"file_name":"/home/users/u6632448/.cargo/registry/src/github.com-1ecc6299db9ec823/glob-0.3.0/src/lib.rs","byte_start":14285,"byte_end":14297,"line_start":434,"line_end":434,"column_start":12,"column_end":24},"name":"PatternError","qualname":"::PatternError","value":"PatternError { pos, msg }","parent":null,"children":[{"krate":0,"index":142},{"krate":0,"index":143}],"decl_id":null,"docs":" A pattern parsing error.\n","sig":null,"attributes":[{"value":"/ A pattern parsing error.","span":{"file_name":"/home/users/u6632448/.cargo/registry/src/github.com-1ecc6299db9ec823/glob-0.3.0/src/lib.rs","byte_start":14189,"byte_end":14217,"line_start":431,"line_end":431,"column_start":1,"column_end":29}},{"value":"allow(missing_copy_implementations)","span":{"file_name":"/home/users/u6632448/.cargo/registry/src/github.com-1ecc6299db9ec823/glob-0.3.0/src/lib.rs","byte_start":14235,"byte_end":14273,"line_start":433,"line_end":433,"column_start":1,"column_end":39}}]},{"kind":"Field","id":{"krate":0,"index":142},"span":{"file_name":"/home/users/u6632448/.cargo/registry/src/github.com-1ecc6299db9ec823/glob-0.3.0/src/lib.rs","byte_start":14377,"byte_end":14380,"line_start":436,"line_end":436,"column_start":9,"column_end":12},"name":"pos","qualname":"::PatternError::pos","value":"usize","parent":{"krate":0,"index":141},"children":[],"decl_id":null,"docs":" The approximate character index of where the error occurred.\n","sig":null,"attributes":[{"value":"/ The approximate character index of where the error occurred.","span":{"file_name":"/home/users/u6632448/.cargo/registry/src/github.com-1ecc6299db9ec823/glob-0.3.0/src/lib.rs","byte_start":14304,"byte_end":14368,"line_start":435,"line_end":435,"column_start":5,"column_end":69}}]},{"kind":"Field","id":{"krate":0,"index":143},"span":{"file_name":"/home/users/u6632448/.cargo/registry/src/github.com-1ecc6299db9ec823/glob-0.3.0/src/lib.rs","byte_start":14438,"byte_end":14441,"line_start":439,"line_end":439,"column_start":9,"column_end":12},"name":"msg","qualname":"::PatternError::msg","value":"&'static str","parent":{"krate":0,"index":141},"children":[],"decl_id":null,"docs":" A message describing the error.\n","sig":null,"attributes":[{"value":"/ A message describing the error.","span":{"file_name":"/home/users/u6632448/.cargo/registry/src/github.com-1ecc6299db9ec823/glob-0.3.0/src/lib.rs","byte_start":14394,"byte_end":14429,"line_start":438,"line_end":438,"column_start":5,"column_end":40}}]},{"kind":"Struct","id":{"krate":0,"index":146},"span":{"file_name":"/home/users/u6632448/.cargo/registry/src/github.com-1ecc6299db9ec823/glob-0.3.0/src/lib.rs","byte_start":16126,"byte_end":16133,"line_start":484,"line_end":484,"column_start":12,"column_end":19},"name":"Pattern","qualname":"::Pattern","value":"Pattern {  }","parent":null,"children":[{"krate":0,"index":147},{"krate":0,"index":148},{"krate":0,"index":149}],"decl_id":null,"docs":" A compiled Unix shell style pattern.","sig":null,"attributes":[{"value":"/ A compiled Unix shell style pattern.","span":{"file_name":"/home/users/u6632448/.cargo/registry/src/github.com-1ecc6299db9ec823/glob-0.3.0/src/lib.rs","byte_start":14786,"byte_end":14826,"line_start":458,"line_end":458,"column_start":1,"column_end":41}},{"value":"/","span":{"file_name":"/home/users/u6632448/.cargo/registry/src/github.com-1ecc6299db9ec823/glob-0.3.0/src/lib.rs","byte_start":14827,"byte_end":14830,"line_start":459,"line_end":459,"column_start":1,"column_end":4}},{"value":"/ - `?` matches any single character.","span":{"file_name":"/home/users/u6632448/.cargo/registry/src/github.com-1ecc6299db9ec823/glob-0.3.0/src/lib.rs","byte_start":14831,"byte_end":14870,"line_start":460,"line_end":460,"column_start":1,"column_end":40}},{"value":"/","span":{"file_name":"/home/users/u6632448/.cargo/registry/src/github.com-1ecc6299db9ec823/glob-0.3.0/src/lib.rs","byte_start":14871,"byte_end":14874,"line_start":461,"line_end":461,"column_start":1,"column_end":4}},{"value":"/ - `*` matches any (possibly empty) sequence of characters.","span":{"file_name":"/home/users/u6632448/.cargo/registry/src/github.com-1ecc6299db9ec823/glob-0.3.0/src/lib.rs","byte_start":14875,"byte_end":14937,"line_start":462,"line_end":462,"column_start":1,"column_end":63}},{"value":"/","span":{"file_name":"/home/users/u6632448/.cargo/registry/src/github.com-1ecc6299db9ec823/glob-0.3.0/src/lib.rs","byte_start":14938,"byte_end":14941,"line_start":463,"line_end":463,"column_start":1,"column_end":4}},{"value":"/ - `**` matches the current directory and arbitrary subdirectories. This","span":{"file_name":"/home/users/u6632448/.cargo/registry/src/github.com-1ecc6299db9ec823/glob-0.3.0/src/lib.rs","byte_start":14942,"byte_end":15017,"line_start":464,"line_end":464,"column_start":1,"column_end":76}},{"value":"/   sequence **must** form a single path component, so both `**a` and `b**`","span":{"file_name":"/home/users/u6632448/.cargo/registry/src/github.com-1ecc6299db9ec823/glob-0.3.0/src/lib.rs","byte_start":15018,"byte_end":15095,"line_start":465,"line_end":465,"column_start":1,"column_end":78}},{"value":"/   are invalid and will result in an error.  A sequence of more than two","span":{"file_name":"/home/users/u6632448/.cargo/registry/src/github.com-1ecc6299db9ec823/glob-0.3.0/src/lib.rs","byte_start":15096,"byte_end":15171,"line_start":466,"line_end":466,"column_start":1,"column_end":76}},{"value":"/   consecutive `*` characters is also invalid.","span":{"file_name":"/home/users/u6632448/.cargo/registry/src/github.com-1ecc6299db9ec823/glob-0.3.0/src/lib.rs","byte_start":15172,"byte_end":15221,"line_start":467,"line_end":467,"column_start":1,"column_end":50}},{"value":"/","span":{"file_name":"/home/users/u6632448/.cargo/registry/src/github.com-1ecc6299db9ec823/glob-0.3.0/src/lib.rs","byte_start":15222,"byte_end":15225,"line_start":468,"line_end":468,"column_start":1,"column_end":4}},{"value":"/ - `[...]` matches any character inside the brackets.  Character sequences","span":{"file_name":"/home/users/u6632448/.cargo/registry/src/github.com-1ecc6299db9ec823/glob-0.3.0/src/lib.rs","byte_start":15226,"byte_end":15303,"line_start":469,"line_end":469,"column_start":1,"column_end":78}},{"value":"/   can also specify ranges of characters, as ordered by Unicode, so e.g.","span":{"file_name":"/home/users/u6632448/.cargo/registry/src/github.com-1ecc6299db9ec823/glob-0.3.0/src/lib.rs","byte_start":15304,"byte_end":15379,"line_start":470,"line_end":470,"column_start":1,"column_end":76}},{"value":"/   `[0-9]` specifies any character between 0 and 9 inclusive. An unclosed","span":{"file_name":"/home/users/u6632448/.cargo/registry/src/github.com-1ecc6299db9ec823/glob-0.3.0/src/lib.rs","byte_start":15380,"byte_end":15456,"line_start":471,"line_end":471,"column_start":1,"column_end":77}},{"value":"/   bracket is invalid.","span":{"file_name":"/home/users/u6632448/.cargo/registry/src/github.com-1ecc6299db9ec823/glob-0.3.0/src/lib.rs","byte_start":15457,"byte_end":15482,"line_start":472,"line_end":472,"column_start":1,"column_end":26}},{"value":"/","span":{"file_name":"/home/users/u6632448/.cargo/registry/src/github.com-1ecc6299db9ec823/glob-0.3.0/src/lib.rs","byte_start":15483,"byte_end":15486,"line_start":473,"line_end":473,"column_start":1,"column_end":4}},{"value":"/ - `[!...]` is the negation of `[...]`, i.e. it matches any characters","span":{"file_name":"/home/users/u6632448/.cargo/registry/src/github.com-1ecc6299db9ec823/glob-0.3.0/src/lib.rs","byte_start":15487,"byte_end":15560,"line_start":474,"line_end":474,"column_start":1,"column_end":74}},{"value":"/   **not** in the brackets.","span":{"file_name":"/home/users/u6632448/.cargo/registry/src/github.com-1ecc6299db9ec823/glob-0.3.0/src/lib.rs","byte_start":15561,"byte_end":15591,"line_start":475,"line_end":475,"column_start":1,"column_end":31}},{"value":"/","span":{"file_name":"/home/users/u6632448/.cargo/registry/src/github.com-1ecc6299db9ec823/glob-0.3.0/src/lib.rs","byte_start":15592,"byte_end":15595,"line_start":476,"line_end":476,"column_start":1,"column_end":4}},{"value":"/ - The metacharacters `?`, `*`, `[`, `]` can be matched by using brackets","span":{"file_name":"/home/users/u6632448/.cargo/registry/src/github.com-1ecc6299db9ec823/glob-0.3.0/src/lib.rs","byte_start":15596,"byte_end":15672,"line_start":477,"line_end":477,"column_start":1,"column_end":77}},{"value":"/   (e.g. `[?]`).  When a `]` occurs immediately following `[` or `[!` then it","span":{"file_name":"/home/users/u6632448/.cargo/registry/src/github.com-1ecc6299db9ec823/glob-0.3.0/src/lib.rs","byte_start":15673,"byte_end":15753,"line_start":478,"line_end":478,"column_start":1,"column_end":81}},{"value":"/   is interpreted as being part of, rather then ending, the character set, so","span":{"file_name":"/home/users/u6632448/.cargo/registry/src/github.com-1ecc6299db9ec823/glob-0.3.0/src/lib.rs","byte_start":15754,"byte_end":15834,"line_start":479,"line_end":479,"column_start":1,"column_end":81}},{"value":"/   `]` and NOT `]` can be matched by `[]]` and `[!]]` respectively.  The `-`","span":{"file_name":"/home/users/u6632448/.cargo/registry/src/github.com-1ecc6299db9ec823/glob-0.3.0/src/lib.rs","byte_start":15835,"byte_end":15914,"line_start":480,"line_end":480,"column_start":1,"column_end":80}},{"value":"/   character can be specified inside a character sequence pattern by placing","span":{"file_name":"/home/users/u6632448/.cargo/registry/src/github.com-1ecc6299db9ec823/glob-0.3.0/src/lib.rs","byte_start":15915,"byte_end":15994,"line_start":481,"line_end":481,"column_start":1,"column_end":80}},{"value":"/   it at the start or the end, e.g. `[abc-]`.","span":{"file_name":"/home/users/u6632448/.cargo/registry/src/github.com-1ecc6299db9ec823/glob-0.3.0/src/lib.rs","byte_start":15995,"byte_end":16043,"line_start":482,"line_end":482,"column_start":1,"column_end":49}}]},{"kind":"Method","id":{"krate":0,"index":111},"span":{"file_name":"/home/users/u6632448/.cargo/registry/src/github.com-1ecc6299db9ec823/glob-0.3.0/src/lib.rs","byte_start":17454,"byte_end":17457,"line_start":537,"line_end":537,"column_start":12,"column_end":15},"name":"new","qualname":"<Pattern>::new","value":"pub fn new(&str) -> Result<Self, PatternError>","parent":null,"children":[],"decl_id":null,"docs":" This function compiles Unix shell style patterns.","sig":null,"attributes":[{"value":"/ This function compiles Unix shell style patterns.","span":{"file_name":"/home/users/u6632448/.cargo/registry/src/github.com-1ecc6299db9ec823/glob-0.3.0/src/lib.rs","byte_start":17320,"byte_end":17373,"line_start":534,"line_end":534,"column_start":5,"column_end":58}},{"value":"/","span":{"file_name":"/home/users/u6632448/.cargo/registry/src/github.com-1ecc6299db9ec823/glob-0.3.0/src/lib.rs","byte_start":17378,"byte_end":17381,"line_start":535,"line_end":535,"column_start":5,"column_end":8}},{"value":"/ An invalid glob pattern will yield a `PatternError`.","span":{"file_name":"/home/users/u6632448/.cargo/registry/src/github.com-1ecc6299db9ec823/glob-0.3.0/src/lib.rs","byte_start":17386,"byte_end":17442,"line_start":536,"line_end":536,"column_start":5,"column_end":61}}]},{"kind":"Method","id":{"krate":0,"index":114},"span":{"file_name":"/home/users/u6632448/.cargo/registry/src/github.com-1ecc6299db9ec823/glob-0.3.0/src/lib.rs","byte_start":22160,"byte_end":22166,"line_start":652,"line_end":652,"column_start":12,"column_end":18},"name":"escape","qualname":"<Pattern>::escape","value":"pub fn escape(&str) -> String","parent":null,"children":[],"decl_id":null,"docs":" Escape metacharacters within the given string by surrounding them in\n brackets. The resulting string will, when compiled into a `Pattern`,\n match the input string and nothing else.\n","sig":null,"attributes":[{"value":"/ Escape metacharacters within the given string by surrounding them in","span":{"file_name":"/home/users/u6632448/.cargo/registry/src/github.com-1ecc6299db9ec823/glob-0.3.0/src/lib.rs","byte_start":21950,"byte_end":22022,"line_start":649,"line_end":649,"column_start":5,"column_end":77}},{"value":"/ brackets. The resulting string will, when compiled into a `Pattern`,","span":{"file_name":"/home/users/u6632448/.cargo/registry/src/github.com-1ecc6299db9ec823/glob-0.3.0/src/lib.rs","byte_start":22027,"byte_end":22099,"line_start":650,"line_end":650,"column_start":5,"column_end":77}},{"value":"/ match the input string and nothing else.","span":{"file_name":"/home/users/u6632448/.cargo/registry/src/github.com-1ecc6299db9ec823/glob-0.3.0/src/lib.rs","byte_start":22104,"byte_end":22148,"line_start":651,"line_end":651,"column_start":5,"column_end":49}}]},{"kind":"Method","id":{"krate":0,"index":115},"span":{"file_name":"/home/users/u6632448/.cargo/registry/src/github.com-1ecc6299db9ec823/glob-0.3.0/src/lib.rs","byte_start":23129,"byte_end":23136,"line_start":683,"line_end":683,"column_start":12,"column_end":19},"name":"matches","qualname":"<Pattern>::matches","value":"pub fn matches(&Self, &str) -> bool","parent":null,"children":[],"decl_id":null,"docs":" Return if the given `str` matches this `Pattern` using the default\n match options (i.e. `MatchOptions::new()`).","sig":null,"attributes":[{"value":"/ Return if the given `str` matches this `Pattern` using the default","span":{"file_name":"/home/users/u6632448/.cargo/registry/src/github.com-1ecc6299db9ec823/glob-0.3.0/src/lib.rs","byte_start":22701,"byte_end":22771,"line_start":671,"line_end":671,"column_start":5,"column_end":75}},{"value":"/ match options (i.e. `MatchOptions::new()`).","span":{"file_name":"/home/users/u6632448/.cargo/registry/src/github.com-1ecc6299db9ec823/glob-0.3.0/src/lib.rs","byte_start":22776,"byte_end":22823,"line_start":672,"line_end":672,"column_start":5,"column_end":52}},{"value":"/","span":{"file_name":"/home/users/u6632448/.cargo/registry/src/github.com-1ecc6299db9ec823/glob-0.3.0/src/lib.rs","byte_start":22828,"byte_end":22831,"line_start":673,"line_end":673,"column_start":5,"column_end":8}},{"value":"/ # Examples","span":{"file_name":"/home/users/u6632448/.cargo/registry/src/github.com-1ecc6299db9ec823/glob-0.3.0/src/lib.rs","byte_start":22836,"byte_end":22850,"line_start":674,"line_end":674,"column_start":5,"column_end":19}},{"value":"/","span":{"file_name":"/home/users/u6632448/.cargo/registry/src/github.com-1ecc6299db9ec823/glob-0.3.0/src/lib.rs","byte_start":22855,"byte_end":22858,"line_start":675,"line_end":675,"column_start":5,"column_end":8}},{"value":"/ ```rust","span":{"file_name":"/home/users/u6632448/.cargo/registry/src/github.com-1ecc6299db9ec823/glob-0.3.0/src/lib.rs","byte_start":22863,"byte_end":22874,"line_start":676,"line_end":676,"column_start":5,"column_end":16}},{"value":"/ use glob::Pattern;","span":{"file_name":"/home/users/u6632448/.cargo/registry/src/github.com-1ecc6299db9ec823/glob-0.3.0/src/lib.rs","byte_start":22879,"byte_end":22901,"line_start":677,"line_end":677,"column_start":5,"column_end":27}},{"value":"/","span":{"file_name":"/home/users/u6632448/.cargo/registry/src/github.com-1ecc6299db9ec823/glob-0.3.0/src/lib.rs","byte_start":22906,"byte_end":22909,"line_start":678,"line_end":678,"column_start":5,"column_end":8}},{"value":"/ assert!(Pattern::new(\"c?t\").unwrap().matches(\"cat\"));","span":{"file_name":"/home/users/u6632448/.cargo/registry/src/github.com-1ecc6299db9ec823/glob-0.3.0/src/lib.rs","byte_start":22914,"byte_end":22971,"line_start":679,"line_end":679,"column_start":5,"column_end":62}},{"value":"/ assert!(Pattern::new(\"k[!e]tteh\").unwrap().matches(\"kitteh\"));","span":{"file_name":"/home/users/u6632448/.cargo/registry/src/github.com-1ecc6299db9ec823/glob-0.3.0/src/lib.rs","byte_start":22976,"byte_end":23042,"line_start":680,"line_end":680,"column_start":5,"column_end":71}},{"value":"/ assert!(Pattern::new(\"d*g\").unwrap().matches(\"doog\"));","span":{"file_name":"/home/users/u6632448/.cargo/registry/src/github.com-1ecc6299db9ec823/glob-0.3.0/src/lib.rs","byte_start":23047,"byte_end":23105,"line_start":681,"line_end":681,"column_start":5,"column_end":63}},{"value":"/ ```","span":{"file_name":"/home/users/u6632448/.cargo/registry/src/github.com-1ecc6299db9ec823/glob-0.3.0/src/lib.rs","byte_start":23110,"byte_end":23117,"line_start":682,"line_end":682,"column_start":5,"column_end":12}}]},{"kind":"Method","id":{"krate":0,"index":116},"span":{"file_name":"/home/users/u6632448/.cargo/registry/src/github.com-1ecc6299db9ec823/glob-0.3.0/src/lib.rs","byte_start":23391,"byte_end":23403,"line_start":689,"line_end":689,"column_start":12,"column_end":24},"name":"matches_path","qualname":"<Pattern>::matches_path","value":"pub fn matches_path(&Self, &Path) -> bool","parent":null,"children":[],"decl_id":null,"docs":" Return if the given `Path`, when converted to a `str`, matches this\n `Pattern` using the default match options (i.e. `MatchOptions::new()`).\n","sig":null,"attributes":[{"value":"/ Return if the given `Path`, when converted to a `str`, matches this","span":{"file_name":"/home/users/u6632448/.cargo/registry/src/github.com-1ecc6299db9ec823/glob-0.3.0/src/lib.rs","byte_start":23228,"byte_end":23299,"line_start":687,"line_end":687,"column_start":5,"column_end":76}},{"value":"/ `Pattern` using the default match options (i.e. `MatchOptions::new()`).","span":{"file_name":"/home/users/u6632448/.cargo/registry/src/github.com-1ecc6299db9ec823/glob-0.3.0/src/lib.rs","byte_start":23304,"byte_end":23379,"line_start":688,"line_end":688,"column_start":5,"column_end":80}}]},{"kind":"Method","id":{"krate":0,"index":118},"span":{"file_name":"/home/users/u6632448/.cargo/registry/src/github.com-1ecc6299db9ec823/glob-0.3.0/src/lib.rs","byte_start":23671,"byte_end":23683,"line_start":696,"line_end":696,"column_start":12,"column_end":24},"name":"matches_with","qualname":"<Pattern>::matches_with","value":"pub fn matches_with(&Self, &str, MatchOptions) -> bool","parent":null,"children":[],"decl_id":null,"docs":" Return if the given `str` matches this `Pattern` using the specified\n match options.\n","sig":null,"attributes":[{"value":"/ Return if the given `str` matches this `Pattern` using the specified","span":{"file_name":"/home/users/u6632448/.cargo/registry/src/github.com-1ecc6299db9ec823/glob-0.3.0/src/lib.rs","byte_start":23564,"byte_end":23636,"line_start":694,"line_end":694,"column_start":5,"column_end":77}},{"value":"/ match options.","span":{"file_name":"/home/users/u6632448/.cargo/registry/src/github.com-1ecc6299db9ec823/glob-0.3.0/src/lib.rs","byte_start":23641,"byte_end":23659,"line_start":695,"line_end":695,"column_start":5,"column_end":23}}]},{"kind":"Method","id":{"krate":0,"index":119},"span":{"file_name":"/home/users/u6632448/.cargo/registry/src/github.com-1ecc6299db9ec823/glob-0.3.0/src/lib.rs","byte_start":23948,"byte_end":23965,"line_start":702,"line_end":702,"column_start":12,"column_end":29},"name":"matches_path_with","qualname":"<Pattern>::matches_path_with","value":"pub fn matches_path_with(&Self, &Path, MatchOptions) -> bool","parent":null,"children":[],"decl_id":null,"docs":" Return if the given `Path`, when converted to a `str`, matches this\n `Pattern` using the specified match options.\n","sig":null,"attributes":[{"value":"/ Return if the given `Path`, when converted to a `str`, matches this","span":{"file_name":"/home/users/u6632448/.cargo/registry/src/github.com-1ecc6299db9ec823/glob-0.3.0/src/lib.rs","byte_start":23812,"byte_end":23883,"line_start":700,"line_end":700,"column_start":5,"column_end":76}},{"value":"/ `Pattern` using the specified match options.","span":{"file_name":"/home/users/u6632448/.cargo/registry/src/github.com-1ecc6299db9ec823/glob-0.3.0/src/lib.rs","byte_start":23888,"byte_end":23936,"line_start":701,"line_end":701,"column_start":5,"column_end":53}}]},{"kind":"Method","id":{"krate":0,"index":121},"span":{"file_name":"/home/users/u6632448/.cargo/registry/src/github.com-1ecc6299db9ec823/glob-0.3.0/src/lib.rs","byte_start":24225,"byte_end":24231,"line_start":709,"line_end":709,"column_start":12,"column_end":18},"name":"as_str","qualname":"<Pattern>::as_str","value":"pub fn as_str(&Self) -> &str","parent":null,"children":[],"decl_id":null,"docs":" Access the original glob pattern.\n","sig":null,"attributes":[{"value":"/ Access the original glob pattern.","span":{"file_name":"/home/users/u6632448/.cargo/registry/src/github.com-1ecc6299db9ec823/glob-0.3.0/src/lib.rs","byte_start":24176,"byte_end":24213,"line_start":708,"line_end":708,"column_start":5,"column_end":42}}]},{"kind":"Struct","id":{"krate":0,"index":244},"span":{"file_name":"/home/users/u6632448/.cargo/registry/src/github.com-1ecc6299db9ec823/glob-0.3.0/src/lib.rs","byte_start":33781,"byte_end":33793,"line_start":965,"line_end":965,"column_start":12,"column_end":24},"name":"MatchOptions","qualname":"::MatchOptions","value":"MatchOptions { case_sensitive, require_literal_separator, require_literal_leading_dot }","parent":null,"children":[{"krate":0,"index":245},{"krate":0,"index":246},{"krate":0,"index":247}],"decl_id":null,"docs":" Configuration options to modify the behaviour of `Pattern::matches_with(..)`.\n","sig":null,"attributes":[{"value":"/ Configuration options to modify the behaviour of `Pattern::matches_with(..)`.","span":{"file_name":"/home/users/u6632448/.cargo/registry/src/github.com-1ecc6299db9ec823/glob-0.3.0/src/lib.rs","byte_start":33579,"byte_end":33660,"line_start":962,"line_end":962,"column_start":1,"column_end":82}},{"value":"allow(missing_copy_implementations)","span":{"file_name":"/home/users/u6632448/.cargo/registry/src/github.com-1ecc6299db9ec823/glob-0.3.0/src/lib.rs","byte_start":33661,"byte_end":33699,"line_start":963,"line_end":963,"column_start":1,"column_end":39}}]},{"kind":"Field","id":{"krate":0,"index":245},"span":{"file_name":"/home/users/u6632448/.cargo/registry/src/github.com-1ecc6299db9ec823/glob-0.3.0/src/lib.rs","byte_start":34052,"byte_end":34066,"line_start":970,"line_end":970,"column_start":9,"column_end":23},"name":"case_sensitive","qualname":"::MatchOptions::case_sensitive","value":"bool","parent":{"krate":0,"index":244},"children":[],"decl_id":null,"docs":" Whether or not patterns should be matched in a case-sensitive manner.\n This currently only considers upper/lower case relationships between\n ASCII characters, but in future this might be extended to work with\n Unicode.\n","sig":null,"attributes":[{"value":"/ Whether or not patterns should be matched in a case-sensitive manner.","span":{"file_name":"/home/users/u6632448/.cargo/registry/src/github.com-1ecc6299db9ec823/glob-0.3.0/src/lib.rs","byte_start":33800,"byte_end":33873,"line_start":966,"line_end":966,"column_start":5,"column_end":78}},{"value":"/ This currently only considers upper/lower case relationships between","span":{"file_name":"/home/users/u6632448/.cargo/registry/src/github.com-1ecc6299db9ec823/glob-0.3.0/src/lib.rs","byte_start":33878,"byte_end":33950,"line_start":967,"line_end":967,"column_start":5,"column_end":77}},{"value":"/ ASCII characters, but in future this might be extended to work with","span":{"file_name":"/home/users/u6632448/.cargo/registry/src/github.com-1ecc6299db9ec823/glob-0.3.0/src/lib.rs","byte_start":33955,"byte_end":34026,"line_start":968,"line_end":968,"column_start":5,"column_end":76}},{"value":"/ Unicode.","span":{"file_name":"/home/users/u6632448/.cargo/registry/src/github.com-1ecc6299db9ec823/glob-0.3.0/src/lib.rs","byte_start":34031,"byte_end":34043,"line_start":969,"line_end":969,"column_start":5,"column_end":17}}]},{"kind":"Field","id":{"krate":0,"index":246},"span":{"file_name":"/home/users/u6632448/.cargo/registry/src/github.com-1ecc6299db9ec823/glob-0.3.0/src/lib.rs","byte_start":34250,"byte_end":34275,"line_start":975,"line_end":975,"column_start":9,"column_end":34},"name":"require_literal_separator","qualname":"::MatchOptions::require_literal_separator","value":"bool","parent":{"krate":0,"index":244},"children":[],"decl_id":null,"docs":" Whether or not path-component separator characters (e.g. `/` on\n Posix) must be matched by a literal `/`, rather than by `*` or `?` or\n `[...]`.\n","sig":null,"attributes":[{"value":"/ Whether or not path-component separator characters (e.g. `/` on","span":{"file_name":"/home/users/u6632448/.cargo/registry/src/github.com-1ecc6299db9ec823/glob-0.3.0/src/lib.rs","byte_start":34079,"byte_end":34146,"line_start":972,"line_end":972,"column_start":5,"column_end":72}},{"value":"/ Posix) must be matched by a literal `/`, rather than by `*` or `?` or","span":{"file_name":"/home/users/u6632448/.cargo/registry/src/github.com-1ecc6299db9ec823/glob-0.3.0/src/lib.rs","byte_start":34151,"byte_end":34224,"line_start":973,"line_end":973,"column_start":5,"column_end":78}},{"value":"/ `[...]`.","span":{"file_name":"/home/users/u6632448/.cargo/registry/src/github.com-1ecc6299db9ec823/glob-0.3.0/src/lib.rs","byte_start":34229,"byte_end":34241,"line_start":974,"line_end":974,"column_start":5,"column_end":17}}]},{"kind":"Field","id":{"krate":0,"index":247},"span":{"file_name":"/home/users/u6632448/.cargo/registry/src/github.com-1ecc6299db9ec823/glob-0.3.0/src/lib.rs","byte_start":34644,"byte_end":34671,"line_start":982,"line_end":982,"column_start":9,"column_end":36},"name":"require_literal_leading_dot","qualname":"::MatchOptions::require_literal_leading_dot","value":"bool","parent":{"krate":0,"index":244},"children":[],"decl_id":null,"docs":" Whether or not paths that contain components that start with a `.`\n will require that `.` appears literally in the pattern; `*`, `?`, `**`,\n or `[...]` will not match. This is useful because such files are\n conventionally considered hidden on Unix systems and it might be\n desirable to skip them when listing files.\n","sig":null,"attributes":[{"value":"/ Whether or not paths that contain components that start with a `.`","span":{"file_name":"/home/users/u6632448/.cargo/registry/src/github.com-1ecc6299db9ec823/glob-0.3.0/src/lib.rs","byte_start":34288,"byte_end":34358,"line_start":977,"line_end":977,"column_start":5,"column_end":75}},{"value":"/ will require that `.` appears literally in the pattern; `*`, `?`, `**`,","span":{"file_name":"/home/users/u6632448/.cargo/registry/src/github.com-1ecc6299db9ec823/glob-0.3.0/src/lib.rs","byte_start":34363,"byte_end":34438,"line_start":978,"line_end":978,"column_start":5,"column_end":80}},{"value":"/ or `[...]` will not match. This is useful because such files are","span":{"file_name":"/home/users/u6632448/.cargo/registry/src/github.com-1ecc6299db9ec823/glob-0.3.0/src/lib.rs","byte_start":34443,"byte_end":34511,"line_start":979,"line_end":979,"column_start":5,"column_end":73}},{"value":"/ conventionally considered hidden on Unix systems and it might be","span":{"file_name":"/home/users/u6632448/.cargo/registry/src/github.com-1ecc6299db9ec823/glob-0.3.0/src/lib.rs","byte_start":34516,"byte_end":34584,"line_start":980,"line_end":980,"column_start":5,"column_end":73}},{"value":"/ desirable to skip them when listing files.","span":{"file_name":"/home/users/u6632448/.cargo/registry/src/github.com-1ecc6299db9ec823/glob-0.3.0/src/lib.rs","byte_start":34589,"byte_end":34635,"line_start":981,"line_end":981,"column_start":5,"column_end":51}}]},{"kind":"Method","id":{"krate":0,"index":135},"span":{"file_name":"/home/users/u6632448/.cargo/registry/src/github.com-1ecc6299db9ec823/glob-0.3.0/src/lib.rs","byte_start":35147,"byte_end":35150,"line_start":999,"line_end":999,"column_start":12,"column_end":15},"name":"new","qualname":"<MatchOptions>::new","value":"pub fn new() -> Self","parent":null,"children":[],"decl_id":null,"docs":" Constructs a new `MatchOptions` with default field values. This is used\n when calling functions that do not take an explicit `MatchOptions`\n parameter.","sig":null,"attributes":[{"value":"/ Constructs a new `MatchOptions` with default field values. This is used","span":{"file_name":"/home/users/u6632448/.cargo/registry/src/github.com-1ecc6299db9ec823/glob-0.3.0/src/lib.rs","byte_start":34706,"byte_end":34781,"line_start":986,"line_end":986,"column_start":5,"column_end":80}},{"value":"/ when calling functions that do not take an explicit `MatchOptions`","span":{"file_name":"/home/users/u6632448/.cargo/registry/src/github.com-1ecc6299db9ec823/glob-0.3.0/src/lib.rs","byte_start":34786,"byte_end":34856,"line_start":987,"line_end":987,"column_start":5,"column_end":75}},{"value":"/ parameter.","span":{"file_name":"/home/users/u6632448/.cargo/registry/src/github.com-1ecc6299db9ec823/glob-0.3.0/src/lib.rs","byte_start":34861,"byte_end":34875,"line_start":988,"line_end":988,"column_start":5,"column_end":19}},{"value":"/","span":{"file_name":"/home/users/u6632448/.cargo/registry/src/github.com-1ecc6299db9ec823/glob-0.3.0/src/lib.rs","byte_start":34880,"byte_end":34883,"line_start":989,"line_end":989,"column_start":5,"column_end":8}},{"value":"/ This function always returns this value:","span":{"file_name":"/home/users/u6632448/.cargo/registry/src/github.com-1ecc6299db9ec823/glob-0.3.0/src/lib.rs","byte_start":34888,"byte_end":34932,"line_start":990,"line_end":990,"column_start":5,"column_end":49}},{"value":"/","span":{"file_name":"/home/users/u6632448/.cargo/registry/src/github.com-1ecc6299db9ec823/glob-0.3.0/src/lib.rs","byte_start":34937,"byte_end":34940,"line_start":991,"line_end":991,"column_start":5,"column_end":8}},{"value":"/ ```rust,ignore","span":{"file_name":"/home/users/u6632448/.cargo/registry/src/github.com-1ecc6299db9ec823/glob-0.3.0/src/lib.rs","byte_start":34945,"byte_end":34963,"line_start":992,"line_end":992,"column_start":5,"column_end":23}},{"value":"/ MatchOptions {","span":{"file_name":"/home/users/u6632448/.cargo/registry/src/github.com-1ecc6299db9ec823/glob-0.3.0/src/lib.rs","byte_start":34968,"byte_end":34986,"line_start":993,"line_end":993,"column_start":5,"column_end":23}},{"value":"/     case_sensitive: true,","span":{"file_name":"/home/users/u6632448/.cargo/registry/src/github.com-1ecc6299db9ec823/glob-0.3.0/src/lib.rs","byte_start":34991,"byte_end":35020,"line_start":994,"line_end":994,"column_start":5,"column_end":34}},{"value":"/     require_literal_separator: false,","span":{"file_name":"/home/users/u6632448/.cargo/registry/src/github.com-1ecc6299db9ec823/glob-0.3.0/src/lib.rs","byte_start":35025,"byte_end":35066,"line_start":995,"line_end":995,"column_start":5,"column_end":46}},{"value":"/     require_literal_leading_dot: false","span":{"file_name":"/home/users/u6632448/.cargo/registry/src/github.com-1ecc6299db9ec823/glob-0.3.0/src/lib.rs","byte_start":35071,"byte_end":35113,"line_start":996,"line_end":996,"column_start":5,"column_end":47}},{"value":"/ }","span":{"file_name":"/home/users/u6632448/.cargo/registry/src/github.com-1ecc6299db9ec823/glob-0.3.0/src/lib.rs","byte_start":35118,"byte_end":35123,"line_start":997,"line_end":997,"column_start":5,"column_end":10}},{"value":"/ ```","span":{"file_name":"/home/users/u6632448/.cargo/registry/src/github.com-1ecc6299db9ec823/glob-0.3.0/src/lib.rs","byte_start":35128,"byte_end":35135,"line_start":998,"line_end":998,"column_start":5,"column_end":12}}]}],"impls":[{"id":0,"kind":"Inherent","span":{"file_name":"/home/users/u6632448/.cargo/registry/src/github.com-1ecc6299db9ec823/glob-0.3.0/src/lib.rs","byte_start":8948,"byte_end":8957,"line_start":272,"line_end":272,"column_start":6,"column_end":15},"value":"","parent":null,"children":[{"krate":0,"index":83},{"krate":0,"index":84},{"krate":0,"index":85}],"docs":"","sig":null,"attributes":[]},{"id":1,"kind":"Direct","span":{"file_name":"/home/users/u6632448/.cargo/registry/src/github.com-1ecc6299db9ec823/glob-0.3.0/src/lib.rs","byte_start":9318,"byte_end":9327,"line_start":289,"line_end":289,"column_start":16,"column_end":25},"value":"","parent":null,"children":[{"krate":0,"index":87},{"krate":0,"index":88}],"docs":"","sig":null,"attributes":[]},{"id":2,"kind":"Direct","span":{"file_name":"/home/users/u6632448/.cargo/registry/src/github.com-1ecc6299db9ec823/glob-0.3.0/src/lib.rs","byte_start":9503,"byte_end":9512,"line_start":299,"line_end":299,"column_start":23,"column_end":32},"value":"","parent":null,"children":[{"krate":0,"index":90}],"docs":"","sig":null,"attributes":[]},{"id":3,"kind":"Direct","span":{"file_name":"/home/users/u6632448/.cargo/registry/src/github.com-1ecc6299db9ec823/glob-0.3.0/src/lib.rs","byte_start":10081,"byte_end":10086,"line_start":320,"line_end":320,"column_start":19,"column_end":24},"value":"","parent":null,"children":[{"krate":0,"index":95},{"krate":0,"index":96}],"docs":"","sig":null,"attributes":[]},{"id":4,"kind":"Direct","span":{"file_name":"/home/users/u6632448/.cargo/registry/src/github.com-1ecc6299db9ec823/glob-0.3.0/src/lib.rs","byte_start":14475,"byte_end":14487,"line_start":442,"line_end":442,"column_start":16,"column_end":28},"value":"","parent":null,"children":[{"krate":0,"index":99}],"docs":"","sig":null,"attributes":[]},{"id":5,"kind":"Direct","span":{"file_name":"/home/users/u6632448/.cargo/registry/src/github.com-1ecc6299db9ec823/glob-0.3.0/src/lib.rs","byte_start":14574,"byte_end":14586,"line_start":448,"line_end":448,"column_start":23,"column_end":35},"value":"","parent":null,"children":[{"krate":0,"index":101}],"docs":"","sig":null,"attributes":[]},{"id":6,"kind":"Direct","span":{"file_name":"/home/users/u6632448/.cargo/registry/src/github.com-1ecc6299db9ec823/glob-0.3.0/src/lib.rs","byte_start":16274,"byte_end":16281,"line_start":491,"line_end":491,"column_start":23,"column_end":30},"value":"","parent":null,"children":[{"krate":0,"index":103}],"docs":"","sig":null,"attributes":[]},{"id":7,"kind":"Direct","span":{"file_name":"/home/users/u6632448/.cargo/registry/src/github.com-1ecc6299db9ec823/glob-0.3.0/src/lib.rs","byte_start":16398,"byte_end":16405,"line_start":497,"line_end":497,"column_start":18,"column_end":25},"value":"","parent":null,"children":[{"krate":0,"index":105},{"krate":0,"index":106}],"docs":"","sig":null,"attributes":[]},{"id":8,"kind":"Inherent","span":{"file_name":"/home/users/u6632448/.cargo/registry/src/github.com-1ecc6299db9ec823/glob-0.3.0/src/lib.rs","byte_start":17306,"byte_end":17313,"line_start":533,"line_end":533,"column_start":6,"column_end":13},"value":"","parent":null,"children":[{"krate":0,"index":111},{"krate":0,"index":114},{"krate":0,"index":115},{"krate":0,"index":116},{"krate":0,"index":118},{"krate":0,"index":119},{"krate":0,"index":121},{"krate":0,"index":122}],"docs":"","sig":null,"attributes":[]},{"id":9,"kind":"Inherent","span":{"file_name":"/home/users/u6632448/.cargo/registry/src/github.com-1ecc6299db9ec823/glob-0.3.0/src/lib.rs","byte_start":34687,"byte_end":34699,"line_start":985,"line_end":985,"column_start":6,"column_end":18},"value":"","parent":null,"children":[{"krate":0,"index":135}],"docs":"","sig":null,"attributes":[]}],"refs":[],"macro_refs":[],"relations":[{"span":{"file_name":"/home/users/u6632448/.cargo/registry/src/github.com-1ecc6299db9ec823/glob-0.3.0/src/lib.rs","byte_start":8948,"byte_end":8957,"line_start":272,"line_end":272,"column_start":6,"column_end":15},"kind":{"Impl":{"id":0}},"from":{"krate":0,"index":136},"to":{"krate":4294967295,"index":4294967295}},{"span":{"file_name":"/home/users/u6632448/.cargo/registry/src/github.com-1ecc6299db9ec823/glob-0.3.0/src/lib.rs","byte_start":9318,"byte_end":9327,"line_start":289,"line_end":289,"column_start":16,"column_end":25},"kind":{"Impl":{"id":1}},"from":{"krate":0,"index":136},"to":{"krate":1,"index":2338}},{"span":{"file_name":"/home/users/u6632448/.cargo/registry/src/github.com-1ecc6299db9ec823/glob-0.3.0/src/lib.rs","byte_start":9503,"byte_end":9512,"line_start":299,"line_end":299,"column_start":23,"column_end":32},"kind":{"Impl":{"id":2}},"from":{"krate":0,"index":136},"to":{"krate":2,"index":9401}},{"span":{"file_name":"/home/users/u6632448/.cargo/registry/src/github.com-1ecc6299db9ec823/glob-0.3.0/src/lib.rs","byte_start":10081,"byte_end":10086,"line_start":320,"line_end":320,"column_start":19,"column_end":24},"kind":{"Impl":{"id":3}},"from":{"krate":0,"index":70},"to":{"krate":2,"index":7646}},{"span":{"file_name":"/home/users/u6632448/.cargo/registry/src/github.com-1ecc6299db9ec823/glob-0.3.0/src/lib.rs","byte_start":14475,"byte_end":14487,"line_start":442,"line_end":442,"column_start":16,"column_end":28},"kind":{"Impl":{"id":4}},"from":{"krate":0,"index":141},"to":{"krate":1,"index":2338}},{"span":{"file_name":"/home/users/u6632448/.cargo/registry/src/github.com-1ecc6299db9ec823/glob-0.3.0/src/lib.rs","byte_start":14574,"byte_end":14586,"line_start":448,"line_end":448,"column_start":23,"column_end":35},"kind":{"Impl":{"id":5}},"from":{"krate":0,"index":141},"to":{"krate":2,"index":9401}},{"span":{"file_name":"/home/users/u6632448/.cargo/registry/src/github.com-1ecc6299db9ec823/glob-0.3.0/src/lib.rs","byte_start":16274,"byte_end":16281,"line_start":491,"line_end":491,"column_start":23,"column_end":30},"kind":{"Impl":{"id":6}},"from":{"krate":0,"index":146},"to":{"krate":2,"index":9401}},{"span":{"file_name":"/home/users/u6632448/.cargo/registry/src/github.com-1ecc6299db9ec823/glob-0.3.0/src/lib.rs","byte_start":16398,"byte_end":16405,"line_start":497,"line_end":497,"column_start":18,"column_end":25},"kind":{"Impl":{"id":7}},"from":{"krate":0,"index":146},"to":{"krate":2,"index":11935}},{"span":{"file_name":"/home/users/u6632448/.cargo/registry/src/github.com-1ecc6299db9ec823/glob-0.3.0/src/lib.rs","byte_start":17306,"byte_end":17313,"line_start":533,"line_end":533,"column_start":6,"column_end":13},"kind":{"Impl":{"id":8}},"from":{"krate":0,"index":146},"to":{"krate":4294967295,"index":4294967295}},{"span":{"file_name":"/home/users/u6632448/.cargo/registry/src/github.com-1ecc6299db9ec823/glob-0.3.0/src/lib.rs","byte_start":34687,"byte_end":34699,"line_start":985,"line_end":985,"column_start":6,"column_end":18},"kind":{"Impl":{"id":9}},"from":{"krate":0,"index":244},"to":{"krate":4294967295,"index":4294967295}}]}